quickserver/__init__.py
quickserver/__main__.py
x0m_quickserver-1.0.0.dist-info/LICENCE
x0m_quickserver-1.0.0.dist-info/METADATA
x0m_quickserver-1.0.0.dist-info/WHEEL
x0m_quickserver-1.0.0.dist-info/entry_points.txt
x0m_quickserver-1.0.0.dist-info/top_level.txt
x0m_quickserver-1.0.0.dist-info/RECORD
